[
  {
    "level": "A1.1",
    "article": "das",
    "word": "Buch",
    "meaning": "book",
    "examples": {
      "Present": "Ich lese das Buch.",
      "Simple Past": "Ich las das Buch.",
      "Perfect": "Ich habe das Buch gelesen."
    },
    "translations": {
      "Present": "I read the book.",
      "Simple Past": "I read the book (past).",
      "Perfect": "I have read the book."
    }
  },
  {
    "level": "A1.2",
    "article": "der",
    "word": "Hund",
    "meaning": "dog",
    "examples": {
      "Present": "Der Hund bellt laut.",
      "Simple Past": "Der Hund bellte laut.",
      "Perfect": "Der Hund hat laut gebellt."
    },
    "translations": {
      "Present": "The dog barks loudly.",
      "Simple Past": "The dog barked loudly.",
      "Perfect": "The dog has barked loudly."
    }
  },
  {
    "level": "A2.1",
    "article": "die",
    "word": "Katze",
    "meaning": "cat",
    "examples": {
      "Present": "Die Katze schläft auf dem Sofa.",
      "Simple Past": "Die Katze schlief auf dem Sofa.",
      "Perfect": "Die Katze hat auf dem Sofa geschlafen."
    },
    "translations": {
      "Present": "The cat sleeps on the sofa.",
      "Simple Past": "The cat slept on the sofa.",
      "Perfect": "The cat has slept on the sofa."
    }
  },
  {
    "level": "A2.2",
    "article": "das",
    "word": "Haus",
    "meaning": "house",
    "examples": {
      "Present": "Das Haus steht am See.",
      "Simple Past": "Das Haus stand am See.",
      "Perfect": "Das Haus hat am See gestanden."
    },
    "translations": {
      "Present": "The house stands by the lake.",
      "Simple Past": "The house stood by the lake.",
      "Perfect": "The house has stood by the lake."
    }
  },
  {
    "level": "B1.1",
    "article": "der",
    "word": "Apfel",
    "meaning": "apple",
    "examples": {
      "Present": "Ich esse einen Apfel.",
      "Simple Past": "Ich aß einen Apfel.",
      "Perfect": "Ich habe einen Apfel gegessen."
    },
    "translations": {
      "Present": "I eat an apple.",
      "Simple Past": "I ate an apple.",
      "Perfect": "I have eaten an apple."
    }
  },
  {
    "level": "B1.2",
    "article": "die",
    "word": "Erfahrung",
    "meaning": "experience",
    "examples": {
      "Present": "Ich sammle Erfahrung.",
      "Simple Past": "Ich sammelte Erfahrung.",
      "Perfect": "Ich habe Erfahrung gesammelt."
    },
    "translations": {
      "Present": "I gain experience.",
      "Simple Past": "I gained experience.",
      "Perfect": "I have gained experience."
    }
  },
  {
    "level": "B2.1",
    "article": "das",
    "word": "Thema",
    "meaning": "topic",
    "examples": {
      "Present": "Wir diskutieren das Thema.",
      "Simple Past": "Wir diskutierten das Thema.",
      "Perfect": "Wir haben das Thema diskutiert."
    },
    "translations": {
      "Present": "We discuss the topic.",
      "Simple Past": "We discussed the topic.",
      "Perfect": "We have discussed the topic."
    }
  },
  {
    "level": "B2.2",
    "article": "der",
    "word": "Vorteil",
    "meaning": "advantage",
    "examples": {
      "Present": "Der Vorteil ist klar.",
      "Simple Past": "Der Vorteil war klar.",
      "Perfect": "Der Vorteil ist klar gewesen."
    },
    "translations": {
      "Present": "The advantage is clear.",
      "Simple Past": "The advantage was clear.",
      "Perfect": "The advantage has been clear."
    }
  },
  {
    "level": "C1.1",
    "article": "die",
    "word": "Entscheidung",
    "meaning": "decision",
    "examples": {
      "Present": "Die Entscheidung fällt schwer.",
      "Simple Past": "Die Entscheidung fiel schwer.",
      "Perfect": "Die Entscheidung ist schwer gefallen."
    },
    "translations": {
      "Present": "The decision is difficult.",
      "Simple Past": "The decision was difficult.",
      "Perfect": "The decision has been difficult."
    }
  },
  {
    "level": "C1.2",
    "article": "das",
    "word": "Ergebnis",
    "meaning": "result",
    "examples": {
      "Present": "Das Ergebnis überzeugt.",
      "Simple Past": "Das Ergebnis überzeugte.",
      "Perfect": "Das Ergebnis hat überzeugt."
    },
    "translations": {
      "Present": "The result convinces.",
      "Simple Past": "The result convinced.",
      "Perfect": "The result has convinced."
    }
  },
  {
    "level": "C2.1",
    "article": "der",
    "word": "Widerspruch",
    "meaning": "contradiction",
    "examples": {
      "Present": "Seine Aussage steht im Widerspruch.",
      "Simple Past": "Seine Aussage stand im Widerspruch.",
      "Perfect": "Seine Aussage hat im Widerspruch gestanden."
    },
    "translations": {
      "Present": "His statement is in contradiction.",
      "Simple Past": "His statement was in contradiction.",
      "Perfect": "His statement has been in contradiction."
    }
  },
  {
    "level": "C2.2",
    "article": "die",
    "word": "Voraussetzung",
    "meaning": "prerequisite",
    "examples": {
      "Present": "Die Voraussetzung ist erfüllt.",
      "Simple Past": "Die Voraussetzung war erfüllt.",
      "Perfect": "Die Voraussetzung ist erfüllt gewesen."
    },
    "translations": {
      "Present": "The prerequisite is met.",
      "Simple Past": "The prerequisite was met.",
      "Perfect": "The prerequisite has been met."
    }
  }
]
